.tensorvis-complete.bash
tensorvis/__version__.py
tensorvis/utils/__init__.py
tensorvis/utils/utils.py
tensorvis/vis.py
tensorvis-1.3.10.dist-info/entry_points.txt
tensorvis-1.3.10.dist-info/WHEEL
tensorvis-1.3.10.dist-info/METADATA
tensorvis-1.3.10.dist-info/RECORD
