Metadata-Version: 2.1
Name: tensorvis
Version: 1.3.10
Summary: Visualisation tool to support my PhD automating the process of gathering data and plotting it
Home-page: https://github.com/npitsillos/tensorplot.git
Author: Nikolas Pitsillos
Author-email: npitsillos@gmail.com
Requires-Python: >=3.7,<4.0
Classifier: Programming Language :: Python :: 3
Classifier: Programming Language :: Python :: 3.10
Classifier: Programming Language :: Python :: 3.7
Classifier: Programming Language :: Python :: 3.8
Classifier: Programming Language :: Python :: 3.9
Requires-Dist: click (>=8.0.0,<9.0.0)
Requires-Dist: kaleido (==0.2.1)
Requires-Dist: pandas (>=1.1.4,<2.0.0)
Requires-Dist: plotly (>=4.14.3,<5.0.0)
Requires-Dist: tensorboard (>=2.4.0,<3.0.0)
Project-URL: Repository, https://github.com/npitsillos/tensorplot.git
